setup.py
salure_helpers/zoho/__init__.py
salure_helpers/zoho/extract_zoho_desk.py
salure_helpers/zoho/upload_zoho_desk.py
salure_helpers_zoho.egg-info/PKG-INFO
salure_helpers_zoho.egg-info/SOURCES.txt
salure_helpers_zoho.egg-info/dependency_links.txt
salure_helpers_zoho.egg-info/not-zip-safe
salure_helpers_zoho.egg-info/requires.txt
salure_helpers_zoho.egg-info/top_level.txt