Metadata-Version: 1.0
Name: salure-helpers-zoho
Version: 0.1.3
Summary: ZOHO wrapper from Salure
Home-page: UNKNOWN
Author: D&A Salure
Author-email: support@salureconnnect.com
License: Salure License
Platform: UNKNOWN
